AUTHORS.rst
CONTRIBUTING.rst
HISTORY.rst
LICENSE
MANIFEST.in
README.rst
setup.cfg
setup.py
django_fwdform.egg-info/PKG-INFO
django_fwdform.egg-info/SOURCES.txt
django_fwdform.egg-info/dependency_links.txt
django_fwdform.egg-info/not-zip-safe
django_fwdform.egg-info/requires.txt
django_fwdform.egg-info/top_level.txt
fwdform/__init__.py
fwdform/admin.py
fwdform/akismet.py
fwdform/apps.py
fwdform/conf.py
fwdform/exceptions.py
fwdform/forms.py
fwdform/helpers.py
fwdform/models.py
fwdform/urls.py
fwdform/views.py
fwdform/migrations/0001_initial.py
fwdform/migrations/__init__.py
fwdform/static/css/fwdform/fwdform.css
fwdform/static/js/fwdform/fwdform.js
fwdform/templates/fwdform/base.html
fwdform/templates/fwdform/error.html
fwdform/templates/fwdform/submission.txt
fwdform/templates/fwdform/thankyou.html