Metadata-Version: 1.1
Name: django-fwdform
Version: 0.1.0
Summary: Simple and painless form processing for static sites.
Home-page: https://github.com/mishbahr/django-fwdform
Author: Mishbah Razzaque
Author-email: mishbahx@gmail.com
License: BSD
Keywords: django-fwdform
Platform: UNKNOWN
Classifier: Development Status :: 4 - Beta
Classifier: Framework :: Django
Classifier: Framework :: Django :: 1.7
Classifier: Framework :: Django :: 1.8
Classifier: Framework :: Django :: 1.9
Classifier: Intended Audience :: Developers
Classifier: License :: OSI Approved :: BSD License
Classifier: Natural Language :: English
Classifier: Programming Language :: Python :: 2
Classifier: Programming Language :: Python :: 2.7
Classifier: Programming Language :: Python :: 3
Classifier: Programming Language :: Python :: 3.3
Classifier: Programming Language :: Python :: 3.4
Classifier: Programming Language :: Python :: 3.5
